easydock/__init__.py
easydock/args_validation.py
easydock/auxiliary.py
easydock/containers.py
easydock/database.py
easydock/docking.py
easydock/easydock_plif.py
easydock/get_sdf_from_dock_db.py
easydock/gnina_dock.py
easydock/make_clean_copy.py
easydock/plif.py
easydock/preparation_for_docking.py
easydock/protonation.py
easydock/qvina_dock.py
easydock/read_input.py
easydock/run_dock.py
easydock/run_dock_obsolete.py
easydock/unipka.py
easydock/vina_dock.py
easydock/vina_dock_cli.py
easydock/vinagpu_dock.py
easydock-1.2.0.dist-info/LICENSE.txt
easydock-1.2.0.dist-info/METADATA
easydock-1.2.0.dist-info/WHEEL
easydock-1.2.0.dist-info/entry_points.txt
easydock-1.2.0.dist-info/top_level.txt
easydock-1.2.0.dist-info/RECORD
