Metadata-Version: 2.1
Name: easydock
Version: 1.2.0
Summary: EasyDock Python module to facilitate molecular docking
Home-page: https://github.com/ci-lab-cz/easydock
Author: Pavel Polishchuk, Guzel Minibaeva, Aleksandra Ivanova
Author-email: pavel_polishchuk@ukr.net
Classifier: Programming Language :: Python :: 3
Classifier: Operating System :: OS Independent
Classifier: Topic :: Scientific/Engineering :: Bio-Informatics
Classifier: Topic :: Scientific/Engineering :: Chemistry
Requires-Python: >=3.6
License-File: LICENSE.txt
Provides-Extra: rdkit
Requires-Dist: rdkit >=2017.09 ; extra == 'rdkit'
